datareader/__init__.py
datareader/cli.py
datareader/reader.py
datareader/formatters/__init__.py
datareader/formatters/base_formatter.py
datareader/formatters/markdown_formatter.py
datareader/processors/__init__.py
datareader/processors/audio_processor.py
datareader/processors/base_processor.py
datareader/processors/markitdown_processor.py
datareader/processors/pdf_processor.py
datareader/processors/pymupdf_processor.py
datareader/processors/url_processor.py
datareader/processors/video_processor.py
keytake_datareader-0.1.8.dist-info/licenses/LICENSE
keytake_datareader-0.1.8.dist-info/METADATA
keytake_datareader-0.1.8.dist-info/WHEEL
keytake_datareader-0.1.8.dist-info/top_level.txt
keytake_datareader-0.1.8.dist-info/RECORD
